smdc/__init__.py
smdc/args.py
smdc/convert.py
smdc/note.py
smdc/parse.py
smdc/server.py
smdc/stream.py
smdc/format/__init__.py
smdc/format/csv.py
smdc/format/cypher.py
smdc/format/format.py
smdc/format/neo4j.py
smdc/format/typed_list.py
smdc/format/util.py
semantic_markdown_converter-0.5.9.dist-info/LICENSE
semantic_markdown_converter-0.5.9.dist-info/METADATA
semantic_markdown_converter-0.5.9.dist-info/WHEEL
semantic_markdown_converter-0.5.9.dist-info/entry_points.txt
semantic_markdown_converter-0.5.9.dist-info/top_level.txt
semantic_markdown_converter-0.5.9.dist-info/RECORD
