Metadata-Version: 2.1
Name: semantic-markdown-converter
Version: 0.5.9
Summary: Converts different typed link formats in Markdown into each other and to external formats. Supports Obsidian Neo4j plugin.
Home-page: https://github.com/HEmile/semantic-markdown-converter
Author: Emile van Krieken
Author-email: emilevankrieken@live.nl
License: MIT
Platform: UNKNOWN
Classifier: Programming Language :: Python :: 3
Classifier: License :: OSI Approved :: MIT License
Classifier: Operating System :: OS Independent
Requires-Python: >=3.6
Requires-Dist: pyyaml
Requires-Dist: tqdm
Requires-Dist: py2neo
Requires-Dist: watchdog (>=1.0.2)
Requires-Dist: markdown
Requires-Dist: mdx-wikilink-plus
